ttech_autofollow/__init__.py
ttech_autofollow/api/__init__.py
ttech_autofollow/api/autofollow_instrument_api.py
ttech_autofollow/api/autofollow_strategy_api.py
ttech_autofollow/api_client.py
ttech_autofollow/api_response.py
ttech_autofollow/client.py
ttech_autofollow/configuration.py
ttech_autofollow/exceptions.py
ttech_autofollow/models/__init__.py
ttech_autofollow/models/autofollow_instrument.py
ttech_autofollow/models/autofollow_strategy.py
ttech_autofollow/models/direction.py
ttech_autofollow/models/error_response.py
ttech_autofollow/models/get_autofollow_instruments_response.py
ttech_autofollow/models/get_autofollow_strategies_response.py
ttech_autofollow/models/get_portfolio_position_response.py
ttech_autofollow/models/get_strategy_signals_response.py
ttech_autofollow/models/get_strategy_stop_signals_response.py
ttech_autofollow/models/instrument_type.py
ttech_autofollow/models/money.py
ttech_autofollow/models/portfolio_position.py
ttech_autofollow/models/post_autofollow_signal_request.py
ttech_autofollow/models/post_autofollow_signal_response.py
ttech_autofollow/models/post_autofollow_stop_signal_request.py
ttech_autofollow/models/post_autofollow_stop_signal_response.py
ttech_autofollow/models/request_acceptance_type.py
ttech_autofollow/models/signal.py
ttech_autofollow/models/stop_order_type.py
ttech_autofollow/models/stop_signal.py
ttech_autofollow/models/strategy_status.py
ttech_autofollow/rest.py
t_tech_autofollow-1.0.0.dist-info/LICENSE
t_tech_autofollow-1.0.0.dist-info/METADATA
t_tech_autofollow-1.0.0.dist-info/WHEEL
t_tech_autofollow-1.0.0.dist-info/RECORD
