Metadata-Version: 2.3
Name: t-tech-autofollow
Version: 1.0.0
Summary: T-Technologies Public Invest Autofollow SDK
License: Apache-2.0
Author: S. Nemets
Requires-Python: >=3.9,<4
Classifier: License :: OSI Approved :: Apache Software License
Classifier: Programming Language :: Python :: 3
Classifier: Programming Language :: Python :: 3.9
Classifier: Programming Language :: Python :: 3.10
Classifier: Programming Language :: Python :: 3.11
Classifier: Programming Language :: Python :: 3.12
Classifier: Programming Language :: Python :: 3.13
Requires-Dist: pydantic (>=2.11.4,<3.0.0)
Requires-Dist: python-dateutil (>=2.9.0.post0,<3.0.0)
